Workbook
Name Aporte: 'Controle de Investimento'!$D$15
Name Patrimonio: 'Controle de Investimento'!$D$18
Name Qtd_anos: 'Controle de Investimento'!$D$16
Name Rendimento_carteira: 'Controle de Investimento'!$D$11
Name Salario: 'Controle de Investimento'!$D$10
Name sugestao_inestimento: 'Controle de Investimento'!$D$12
Name Taxa_mensal: 'Controle de Investimento'!$D$17

Sheet Controle de Investimento
B9: CONFIGURAÇÕES
B10: Salário | D10: 2000
B11: Rendimento Carteira | D11: 0.006
B12: Sugestão de Investimento (30%) | D12: =D10*30% -> 600
B14: INVESTIMENTO MENSAL
B15: Quanto investir por mês ? | D15: =sugestao_inestimento -> 600
B16: Por quantos anos investir ? | D16: 5
B17: Taxa de rendimento mensal ? | D17: 0.01079
B18: Patrimônio acumulado ? | D18: =FV(Taxa_mensal,Qtd_anos*12,Aporte*-1) -> 50266.148
B19: Dividendos mensais ? | D19: =Patrimonio*Rendimento_carteira -> 301.59689
B21: Cenários | D21: Dividendo
A22: 2 | B22: Quanto eu teria em 2 Anos ? | C22: =FV($D$17,$A22*12,$D$15*-1) -> 16336.576 | D22: =C22*Rendimento_carteira -> 98.019458
A23: 5 | B23: Quanto eu teria em 5 Anos ? | C23: =FV($D$17,$A23*12,$D$15*-1) -> 50266.148 | D23: =C23*Rendimento_carteira -> 301.59689
A24: 10 | B24: Quanto eu teria em 10 Anos ? | C24: =FV($D$17,$A24*12,$D$15*-1) -> 145970.53 | D24: =C24*Rendimento_carteira -> 875.82317
A25: 20 | B25: Quanto eu teria em 20 Anos ? | C25: =FV($D$17,$A25*12,$D$15*-1) -> 675119.04 | D25: =C25*Rendimento_carteira -> 4050.7142
A26: 30 | B26: Quanto eu teria em 30 Anos ? | C26: =FV($D$17,$A26*12,$D$15*-1) -> 2593301.8 | D26: =C26*Rendimento_carteira -> 15559.811
B28: PERFIL | C28: Moderado
B29: VALOR A SER INVESTIDO POR MÊS | C29: =Aporte -> 600
B31: TIPO DE FII | C31: Pertcentual Sugerido | D31: Valores
B32: PAPEL | C32: =VLOOKUP($C$28&"-"&B32,'Tabela de apoio'!$A$2:$D$20,4,FALSE) -> 0.32 | D32: =C32*$C$29 -> 192
B33: TIJOLO | C33: =VLOOKUP($C$28&"-"&B33,'Tabela de apoio'!$A$2:$D$20,4,FALSE) -> 0.4 | D33: =C33*$C$29 -> 240
B34: HIBRIDOS | C34: =VLOOKUP($C$28&"-"&B34,'Tabela de apoio'!$A$2:$D$20,4,FALSE) -> 0.08 | D34: =C34*$C$29 -> 48
B35: FOFs | C35: =VLOOKUP($C$28&"-"&B35,'Tabela de apoio'!$A$2:$D$20,4,FALSE) -> 0.1 | D35: =C35*$C$29 -> 60
B36: DESENVOLVIMENTO | C36: =VLOOKUP($C$28&"-"&B36,'Tabela de apoio'!$A$2:$D$20,4,FALSE) -> 0.1 | D36: =C36*$C$29 -> 60
B37: HOTELARIAS | C37: =VLOOKUP($C$28&"-"&B37,'Tabela de apoio'!$A$2:$D$20,4,FALSE) -> 0 | D37: =C37*$C$29 -> 0
C38: =SUM(C32:C37) -> 1 | D38: =SUM(D32:D37) -> 600

Sheet Tabela de apoio
A2: CHAVE | B2: PERFIL | C2: TIPO DE FII | D2: %
A3: =B3&"-"&C3 -> Conservador-PAPEL | B3: Conservador | C3: PAPEL | D3: 0.3 | G3: CHAVE | H3: %
A4: =B4&"-"&C4 -> Conservador-TIJOLO | B4: Conservador | C4: TIJOLO | D4: 0.5 | G4: Moderado-TIJOLO | H4: =VLOOKUP(G4,$A:$D,4,FALSE) -> 0.4
A5: =B5&"-"&C5 -> Conservador-HIBRIDOS | B5: Conservador | C5: HIBRIDOS | D5: 0.1
A6: =B6&"-"&C6 -> Conservador-FOFs | B6: Conservador | C6: FOFs | D6: 0.1
A7: =B7&"-"&C7 -> Conservador-DESENVOLVIMENTO | B7: Conservador | C7: DESENVOLVIMENTO | D7: 0
A8: =B8&"-"&C8 -> Conservador-HOTELARIAS | B8: Conservador | C8: HOTELARIAS | D8: 0
A9: =B9&"-"&C9 -> Moderado-PAPEL | B9: Moderado | C9: PAPEL | D9: 0.32
A10: =B10&"-"&C10 -> Moderado-TIJOLO | B10: Moderado | C10: TIJOLO | D10: 0.4
A11: =B11&"-"&C11 -> Moderado-HIBRIDOS | B11: Moderado | C11: HIBRIDOS | D11: 0.08
A12: =B12&"-"&C12 -> Moderado-FOFs | B12: Moderado | C12: FOFs | D12: 0.1
A13: =B13&"-"&C13 -> Moderado-DESENVOLVIMENTO | B13: Moderado | C13: DESENVOLVIMENTO | D13: 0.1
A14: =B14&"-"&C14 -> Moderado-HOTELARIAS | B14: Moderado | C14: HOTELARIAS | D14: 0
A15: =B15&"-"&C15 -> Agressivo-PAPEL | B15: Agressivo | C15: PAPEL | D15: 0.5
A16: =B16&"-"&C16 -> Agressivo-TIJOLO | B16: Agressivo | C16: TIJOLO | D16: 0.1
... A20: =B20&"-"&C20 -> Agressivo-HOTELARIAS | B20: Agressivo | C20: HOTELARIAS | D20: 0.1
